label_studio_ml/__init__.py
label_studio_ml/api.py
label_studio_ml/exceptions.py
label_studio_ml/helpers.py
label_studio_ml/model.py
label_studio_ml/server.py
label_studio_ml/utils.py
label_studio_ml/default_configs/Dockerfile
label_studio_ml/default_configs/README.md
label_studio_ml/default_configs/_wsgi.py.tmpl
label_studio_ml/default_configs/docker-compose.yml
label_studio_ml/default_configs/requirements.txt
label_studio_ml/tests/__init__.py
label_studio_ml/tests/test_basic.py
label_studio_ml-1.0.8.dist-info/LICENSE
label_studio_ml-1.0.8.dist-info/METADATA
label_studio_ml-1.0.8.dist-info/WHEEL
label_studio_ml-1.0.8.dist-info/entry_points.txt
label_studio_ml-1.0.8.dist-info/top_level.txt
label_studio_ml-1.0.8.dist-info/RECORD
