Metadata-Version: 2.1
Name: label-studio-ml
Version: 1.0.8
Summary: Label Studio ML backend
Home-page: https://github.com/heartexlabs/label-studio-ml-backend
Author: Heartex
Author-email: hello@heartex.ai
License: UNKNOWN
Platform: UNKNOWN
Classifier: Programming Language :: Python :: 3
Classifier: License :: OSI Approved :: MIT License
Classifier: Operating System :: OS Independent
Requires-Python: >=3.6
Requires-Dist: Flask (==1.1.2)
Requires-Dist: Jinja2 (==3.0.3)
Requires-Dist: Pillow
Requires-Dist: appdirs (>=1.4.3)
Requires-Dist: attr (==0.3.1)
Requires-Dist: attrs (>=19.2.0)
Requires-Dist: colorama (>=0.4.4)
Requires-Dist: itsdangerous (==2.0.1)
Requires-Dist: label-studio-tools (==0.0.0.dev11)
Requires-Dist: lxml (>=4.2.5)
Requires-Dist: requests (<3,>=2.22.0)
Requires-Dist: werkzeug (==2.0.2)
